velora/__init__.py
velora/cli.py
velora/client.py
velora/server.py
velora/share.py
velora_chat-1.0.1.dist-info/licenses/LICENSE
velora_chat-1.0.1.dist-info/METADATA
velora_chat-1.0.1.dist-info/WHEEL
velora_chat-1.0.1.dist-info/entry_points.txt
velora_chat-1.0.1.dist-info/top_level.txt
velora_chat-1.0.1.dist-info/RECORD
