Metadata-Version: 2.4
Name: velora-chat
Version: 1.0.1
Summary: Simple file sharing and chat over TCP sockets
Home-page: https://github.com/pavansai-tanguturi/Velora
Author: Pavan Sai Tanguturi
Author-email: pavansai.tanguturi@gmail.com
Project-URL: Bug Reports, https://github.com/pavansai-tanguturi/Velora/issues
Project-URL: Source, https://github.com/pavansai-tanguturi/Velora
Project-URL: Documentation, https://github.com/pavansai-tanguturi/Velora#readme
Keywords: chat file-sharing tcp sockets networking p2p
Classifier: Development Status :: 4 - Beta
Classifier: Intended Audience :: End Users/Desktop
Classifier: License :: OSI Approved :: MIT License
Classifier: Operating System :: OS Independent
Classifier: Programming Language :: Python :: 3
Classifier: Programming Language :: Python :: 3.7
Classifier: Programming Language :: Python :: 3.8
Classifier: Programming Language :: Python :: 3.9
Classifier: Programming Language :: Python :: 3.10
Classifier: Programming Language :: Python :: 3.11
Classifier: Topic :: Communications :: Chat
Classifier: Topic :: Internet
Requires-Python: >=3.7
License-File: LICENSE
Provides-Extra: dev
Requires-Dist: pytest>=6.0; extra == "dev"
Requires-Dist: black>=21.0; extra == "dev"
Requires-Dist: flake8>=3.8; extra == "dev"
Dynamic: author
Dynamic: author-email
Dynamic: classifier
Dynamic: description
Dynamic: description-content-type
Dynamic: home-page
Dynamic: keywords
Dynamic: license-file
Dynamic: project-url
Dynamic: provides-extra
Dynamic: requires-python
Dynamic: summary
